{
  "hash": "e898631d",
  "browserHash": "77651b98",
  "optimized": {
    "react": {
      "src": "../../node_modules/react/index.js",
      "file": "react.js",
      "fileHash": "57bcdd3b",
      "needsInterop": true
    },
    "react-dom/client": {
      "src": "../../node_modules/react-dom/client.js",
      "file": "react-dom_client.js",
      "fileHash": "ea808af6",
      "needsInterop": true
    },
    "react-router-dom": {
      "src": "../../node_modules/react-router-dom/dist/index.js",
      "file": "react-router-dom.js",
      "fileHash": "d65f1f75",
      "needsInterop": false
    },
    "axios": {
      "src": "../../node_modules/axios/index.js",
      "file": "axios.js",
      "fileHash": "ca4aae64",
      "needsInterop": false
    }
  },
  "chunks": {
    "chunk-ZAUFE7H7": {
      "file": "chunk-ZAUFE7H7.js"
    },
    "chunk-UXIASGQL": {
      "file": "chunk-UXIASGQL.js"
    }
  }
}